Workbook

Sheet Executive Summary
A1: Executive Summary: 5 x $50K Futures Accounts
A2: Research date: June 06, 2026. Verify checkout and rules immediately before purchase.
A4: Recommendation | B4: Best overall for the stated five-account objective: Tradeify Select 50K. It combines a permanent 5-account bundle discount, one-time pricing, no activation fee, EOD drawdown, a selectable payout path, and current official documentation that is unusually clear.
A6: Top 3 | B6: 1) Tradeify Select 50K 2) Topstep 50K Standard 3) LucidPro 50K
A7: Best low-cost normal path | B7: Topstep: $49/month + $149 activation per account; Tradeify is stronger if avoiding monthly rebills.
A8: Best payout-friendly | B8: Take Profit Trader for daily access after its buffer; Tradeify/Lucid are stronger blends of cost and payout terms.
A9: Best rules / transparency | B9: Topstep for mature documentation; Tradeify for concise current product documentation.
A10: Best for copying 5 accounts | B10: Tradeify, then Topstep. Confirm copier and anti-hedging details in writing before scaling.
A11: Highest-risk / verify | B11: Bulenox and Elite Trader Funding. Apex pricing is also highly promotion-sensitive.
A12: Not eligible for the goal | B12: MFFU 50K Flex currently caps new traders at 3 sim-funded Flex accounts; Alpha also states 3 qualified accounts; Earn2Trade is not a stacking model.
A13: Core red flag | B13: The advertised $50K is not true risk capital. Practical risk budget is usually the $2K-$2.5K drawdown, and payout withdrawals often shrink that cushion.
A16: Top Firms by Weighted Score
A17: Rank | B17: Company | C17: Score / 100 | D17: Cost to First Payout x5 | E17: Max First Payout x5 Net | F17: Five-Account Fit
A18: 1 | B18: Tradeify | C18: ='Scores & Dashboard'!L8 | D18: ='Five Account Cost Model'!I7 | E18: ='Five Account Cost Model'!L7 | F18: Yes
A19: 2 | B19: Lucid Trading | C19: ='Scores & Dashboard'!L9 | D19: ='Five Account Cost Model'!I8 | E19: ='Five Account Cost Model'!L8 | F19: Yes
A20: 3 | B20: Topstep | C20: ='Scores & Dashboard'!L10 | D20: ='Five Account Cost Model'!I9 | E20: ='Five Account Cost Model'!L9 | F20: Yes (5 active XFA max; verify purchase limits)
A21: 4 | B21: Take Profit Trader | C21: ='Scores & Dashboard'!L11 | D21: ='Five Account Cost Model'!I10 | E21: ='Five Account Cost Model'!L10 | F21: Yes
A22: 5 | B22: Apex Trader Funding | C22: ='Scores & Dashboard'!L6 | D22: ='Five Account Cost Model'!I5 | E22: ='Five Account Cost Model'!L5 | F22: Yes
A23: 6 | B23: MyFundedFutures | C23: ='Scores & Dashboard'!L12 | D23: ='Five Account Cost Model'!I11 | E23: ='Five Account Cost Model'!L11 | F23: No (new 50K Flex sim-funded cap is 3)
A26: Method / Caveats
A27: • Normal list price is used for cost scoring. Promo prices are shown separately because codes and discounts change frequently.
A28: • Cost to first payout means cash fees paid, assuming a first-month pass and no resets. Required trading profit/buffer is shown separately.
A29: • Maximum payout values are current stated cycle caps or a conservative modeling amount where the firm says payouts are uncapped.
A30: • Review ratings are snapshots from Trustpilot on the research date and are not treated as proof. Complaint themes are allegations/themes, not adjudicated facts.
A31: • All futures trading and evaluation fees involve substantial loss risk. This workbook is research, not financial, tax, or legal advice.

Sheet Full Comparison
A1: 50K Futures Prop Firm Full Comparison
A2: Public information researched as of 2026-06-06. Normal prices drive scoring; promos are separate.
A4: Company | B4: Plan | C4: Account Size | D4: Normal Eval Price | E4: Promo / 5-Pack Price | F4: Billing | G4: Activation Fee | H4: Funded Monthly Fee | I4: Max Accounts | J4: Five Funded Feasible? | K4: Copy Trading | L4: Platforms | M4: Markets | N4: Profit Target | O4: Max Drawdown | P4: Daily Loss Limit | Q4: Drawdown Type | R4: Min Eval Days | S4: Consistency | T4: News Trading | U4: Overnight | V4: Weekend | W4: Starting Contracts | X4: Max Contracts | Y4: Automation / Bots | Z4: First Payout Eligibility | AA4: Payout Days | AB4: Min Payout | AC4: Max First Payout / Acct | AD4: Recurring Payout Cap | AE4: Profit Split | AF4: Payout Frequency | AG4: Buffer | AH4: Payout Effect | AI4: Tax / Contractor | AJ4: Trustpilot | AK4: Review Count | AL4: Risk Grade | AM4: Common Complaints | AN4: Common Praise | AO4: Longevity | AP4: Transparency Note | AQ4: Needs Verification | AR4: Primary Sources
A5: Apex Trader Funding | B5: 50K EOD Evaluation | C5: 50000 | D5: 450 | E5: 45 | F5: One-time / 30-day assessment | G5: 119 | H5: 0 | I5: 20 | J5: Yes | K5: Yes, own accounts; avoid prohibited coordination/hedging | L5: Rithmic/Tradovate ecosystem; NinjaTrader, TradingView, Quantower, Sierra Chart | M5: CME/CBOT/NYMEX/COMEX futures; verify product list | N5: 3000 | O5: 2000 | P5: $1,000 fixed session DLL | Q5: EOD trailing; enforced next session | R5: 1 | S5: None to pass; 50% at payout | T5: Allowed, subject to conduct rules | U5: Intraday only; flat by close | V5: No | W5: 6 (official support page table should be rechecked at checkout) | X5: 6 | Y5: Restricted; verify current prohibited-conduct policy | Z5: After 5 qualifying days at $250+ each | AA5: 5 | AB5: 500 | AC5: 1500 | AD5: Payouts 1-6: $1.5k, $1.5k, $2k, $2.5k, $2.5k, $3k | AE5: 1 | AF5: Up to weekly | AG5: $2,100 safety net; $52,600 balance to request $500 | AH5: Only profit above safety net withdrawable; PA closes after payout 6 | AI5: Needs verification | AJ5: 4.3 | AK5: 19517 | AL5: Medium | AM5: Historical payout-review/rule-change complaints; promo/base pricing changes; strict conduct rules | AN5: Large community, broad platform support, 100% current payout split, up to 20 accounts | AO5: Operating since 2021 | AP5: 2026 program redesign; price is volatile and promo-led | AQ5: Normal $450 and $119 activation are volatile; confirm checkout before purchase. | AR5: https://support.apextraderfunding.com/hc/en-us/articles/46724640813083-EOD-Evaluations https://support.apextraderfunding.com/hc/en-us/articles/47205823183003-EOD-Payouts https://propfirmmatch.com/futures/prop-firm-challenges/apex-trader-funding-standard-eod-1-step-50k https://www.trustpilot.com/review/apextraderfunding.com
A6: Alpha Futures | B6: 50K Standard Evaluation | C6: 50000 | D6: 79 | F6: Monthly | G6: 149 | H6: 0 | I6: 3 | J6: No (3 qualified max) | K6: Own-account copying may be supported; copying another trader prohibited | L6: Tradovate/Rithmic options; platform details need verification | M6: CME futures; verify exact list | N6: 3000 | O6: 2000 | P6: None eval; 2% daily loss guard qualified | Q6: EOD trailing, locks near starting balance | R6: 2 | S6: 50% eval; 40% Standard qualified | T6: Eval yes; funded varies by plan | U6: No; flat by 4:20 PM ET | V6: No | W6: Scaling plan | X6: 5 minis / 50 micros | Y6: Algorithmic support reported; verify copier/bot policy | Z6: After 5 winning days of $200+ | AA6: 5 | AB6: 200 | AC6: 1500 | AD6: $1,500/request on current 50K plan shown | AE6: 0.9 | AF6: Up to 4x/month | AG6: May withdraw up to 50% of profit/request | AH6: Drawdown protection remains important | AI6: Needs verification | AJ6: 4.9 | AK6: 3952 | AL6: Medium | AM6: New proprietary platform issues; plan naming/pricing changes; consistency complexity | AN6: Very high recent support ratings, EOD drawdown, fast support | AO6: Newer firm; shorter operating history than Topstep/Earn2Trade | AP6: Current site and help-center plan labels conflict in places | AQ6: Current site displays multiple plan variants. Confirm Standard price, activation fee, and five-account objective. | AR6: https://help.alpha-futures.com/en/articles/9491980-alpha-futures-evaluation-qualified-trader-overview https://alpha-futures.com/how-it-works https://alpha-futures.com/terms-and-conditions https://www.trustpilot.com/review/alpha-futures.com
A7: Tradeify | B7: 50K Select Evaluation | C7: 50000 | D7: 165 | E7: 156.75 | F7: One-time; 5-account bundle gets 5% off | G7: 0 | H7: 0 | I7: 5 | J7: Yes | K7: Yes across own accounts; no hedging/circumvention | L7: Tradovate, Rithmic, WealthCharts; NinjaTrader, TradingView, Quantower, Sierra Chart | M7: CME-group futures; verify exact broker product list | N7: 3000 | O7: 2000 | P7: None in Select eval/Flex funded | Q7: EOD trailing; locks at $50,100 | R7: 3 | S7: 40% eval; none on Select Flex funded | T7: Allowed with restrictions around prohibited conduct | U7: Needs verification | V7: No | W7: 2 minis / 20 micros funded | X7: 4 minis / 40 micros | Y7: Copiers supported; automation policy needs verification | Z7: Select Flex after 5 winning days; Daily path can qualify daily | AA7: 5 | AB7: 250 | AC7: 2000 | AD7: Flex: generally 50% of profit; Daily capped $1,000 on 50K | AE7: 0.9 | AF7: Daily eligibility depending on selected path | AG7: Path-specific; Select Flex lock trigger $52,100 | AH7: MLL locks at $50,100 after threshold/payout mechanics | AI7: Needs verification | AJ7: 4.6 | AK7: 2961 | AL7: Low | AM7: Some KYC/account closure and support-resolution complaints; rules have evolved quickly | AN7: Fast payouts/support, one-time pricing, permanent five-pack discount, flexible payout path | AO7: Launched 2024 | AP7: Excellent current pricing/rules documentation | AQ7: Overnight and automation specifics should be confirmed for selected broker/path. | AR7: https://help.tradeify.co/en/articles/14369021-tradeify-pricing-reference https://help.tradeify.co/en/articles/12853921-select-evaluation-accounts https://help.tradeify.co/en/articles/12853966-select-flex-and-select-daily-payout-policies https://www.trustpilot.com/review/tradeify.co
A8: Lucid Trading | B8: 50K LucidPro Evaluation | C8: 50000 | D8: 185 | E8: 129.5 | F8: One-time | G8: 0 | H8: 0 | I8: 5 | J8: Yes | K8: Own-account copying appears supported; confirm current automation policy | L8: NinjaTrader, Tradovate, Rithmic, MotiveWave, Quantower | M8: CME-group futures; verify product list | N8: 3000 | O8: 2000 | P8: $1,200 | Q8: EOD trailing | R8: 1 | S8: None eval; 40% funded payout cycle | T8: Needs verification by plan | U8: Needs verification | V8: No | W8: 4 minis / 40 micros | X8: 4 minis / 40 micros | Y8: Needs verification in writing | Z8: Any day after $500 cycle profit, 40% consistency, and buffer | AA8: 3 | AB8: 500 | AC8: 2000 | AD8: $2,500 from payout 2 onward | AE8: 0.9 | AF8: On demand; no fixed window | AG8: $52,100; payout only above buffer | AH8: Payout reduces cushion above locked loss floor | AI8: Needs verification | AJ8: 4.7 | AK8: 4125 | AL8: Medium | AM8: Some closures/automation disputes and support delays; company is relatively new | AN8: Very fast payout reports, clean dashboard, clear payout article, no activation fee | AO8: Operating since 2025 | AP8: Good help center; checkout pricing/promos change | AQ8: Obtain written confirmation for bots/copiers, news and overnight policy. | AR8: https://www.lucidtrading.com/ https://lucidtrading.com/product/lucidtest-50k/ https://support.lucidtrading.com/en/articles/12890092-lucidpro-payouts https://www.trustpilot.com/review/lucidtrading.com
A9: Topstep | B9: 50K Standard Trading Combine | C9: 50000 | D9: 49 | F9: Monthly | G9: 149 | H9: 0 | I9: 5 | J9: Yes (5 active XFA max; verify purchase limits) | K9: TopstepX trade copier available; strict no cross-account hedging | L9: TopstepX; supported third-party availability varies | M9: Major CME-group futures supported | N9: 3000 | O9: 2000 | P9: Optional soft DLL discount; no required DLL in Combine | Q9: Trailing Maximum Loss Limit based on balance | R9: 2 | S9: 50% Combine; choose Standard or 40% Consistency XFA | T9: Generally allowed; follow permitted trading hours | U9: No; intraday futures hours | V9: No | W9: Scaling plan in funded | X9: 5 minis / 50 micros in Combine | Y9: Trade copier supported; automation subject to prohibited-conduct rules | Z9: Standard: 5 days $150+; Consistency: 3 days plus 40% | AA9: 5 | AB9: 125 | AC9: 2000 | AD9: $2,000 Standard / $3,000 Consistency per request on new 50K | AE9: 0.9 | AF9: Weekly; daily after 30 winning live days | AG9: Can request 50% of account balance/profit subject to cap | AH9: Payout can reduce buying power and account cushion | AI9: Contractor payout process; verify current tax provider | AJ9: 3.5 | AK9: 14166 | AL9: Low | AM9: Strict hedging enforcement, subscription billing complaints, platform incidents | AN9: 12+ year history, real live progression, strong education, clear official help center | AO9: Founded 2012 | AP9: Best-in-class official documentation, though rules update often | AQ9: Confirm current XFA count and selected payout path immediately before purchase. | AR9: https://help.topstep.com/en/articles/9208217-topstep-pricing https://help.topstep.com/en/articles/8284197-trading-combine-parameters https://help.topstep.com/en/articles/8284233-topstep-payout-policy/ https://www.trustpilot.com/review/topstep.com
A10: Take Profit Trader | B10: 50K Test | C10: 50000 | D10: 170 | E10: 85 | F10: Monthly | G10: 130 | H10: 0 | I10: 5 | J10: Yes | K10: Yes across own accounts; no hedging | L10: Rithmic/Tradovate; NinjaTrader, TradingView, Quantower and others | M10: CME-group futures | N10: 3000 | O10: 2000 | P10: None on current Test; confirm at checkout | Q10: EOD trailing in Test; PRO mechanics tighten around buffer | R10: 5 | S10: 50% Test; none PRO | T10: Allowed | U10: No | V10: No | W10: Scaling plan | X10: 6 minis / 60 micros | Y10: Copiers allowed; bots/EAs restricted | Z10: Day one after reaching $52,000 buffer | AA10: 1 | AB10: 0 | AC10: 5000 | AD10: No stated cycle cap above buffer; firm may move trader to PRO+ live | AE10: 0.8 | AF10: Daily/on demand | AG10: $2,000 buffer; normal withdrawals only once balance reaches $52,000 | AH10: Withdrawing above buffer preserves floor; inside-buffer withdrawal generally terminates account | AI10: Needs verification | AJ10: 4.4 | AK10: 9562 | AL10: Medium | AM10: PRO+ transition/support delays; conflicting third-party drawdown figures; monthly cost | AN10: Daily withdrawals, long payout history, responsive support, clear core buffer concept | AO10: Operating since 2022 | AP10: Official help center clear on payouts; public pricing page less searchable | AQ10: Confirm current $2,000 drawdown, $130 activation, and PRO+ transition policy. | AR10: https://funded.now/propfirm/takeprofit-trader/50000 https://takeprofittraderhelp.zendesk.com/hc/en-us/articles/15172219527581-PRO-Account-Profit-Split-Withdrawal-Rules https://www.trustpilot.com/review/takeprofittrader.com
A11: MyFundedFutures | B11: 50K Flex | C11: 50000 | D11: 153 | E11: 77 | F11: Monthly | G11: 0 | H11: 0 | I11: 3 | J11: No (new 50K Flex sim-funded cap is 3) | K11: Own-account copier supported subject to anti-hedging rules | L11: NinjaTrader, TradingView, Quantower, Tradovate and partner platforms | M11: CME/CBOT/NYMEX/COMEX futures | N11: 3000 | O11: 2000 | P11: None (optional lower-priced DLL add-on variant) | Q11: EOD trailing in eval and Flex sim-funded | R11: 2 | S11: 50% eval only; none payout stage | T11: Allowed | U11: Needs verification | V11: No | W11: 2 minis / 20 micros | X11: 5 minis / 50 micros after scaling | Y11: Copiers supported; bot policy needs verification | Z11: 5 days at $150+ net | AA11: 5 | AB11: 500 | AC11: 2000 | AD11: 50% of net profit up to $2,000/cycle; max 5 sim payouts | AE11: 0.8 | AF11: Weekly/performance based | AG11: No buffer requirement | AH11: After first payout max loss becomes fixed at $100 | AI11: Needs verification | AJ11: 4.9 | AK11: 18858 | AL11: Medium | AM11: Frequent plan changes; strict post-payout $100 loss floor; KYC/support complaints | AN11: No payout buffer, strong support ratings, clear current plan page, path to live after 5 payouts | AO11: Operating since 2023 | AP11: Current pages are detailed but product lineup changes frequently | AQ11: Not suitable for five funded 50K Flex accounts under the current 3-account cap. | AR11: https://myfundedfutures.com/plans/flex https://help.myfundedfutures.com/en/articles/11802636-traders-evaluation-simplified https://www.trustpilot.com/review/myfundedfutures.com
A12: Bulenox | B12: 50K Option 2 EOD/Scaling | C12: 50000 | D12: 175 | F12: Monthly | G12: 148 | H12: 0 | I12: 3 | J12: Needs verification; post-pass gating reported | K12: Needs verification | L12: Rithmic ecosystem; platform list shown by icons, verify exact support | M12: Broad CME-group futures list | N12: 3000 | O12: 2500 | P12: $1,100 soft daily suspension on Option 2 | Q12: EOD trailing/scaling | R12: 5 | S12: Consistency applies in Master payout stage; exact current % needs verification | T12: Needs verification | U12: Limited micros only on legacy help text | V12: No | W12: 2 minis | X12: 7 after scaling | Y12: Needs verification | Z12: After 10 individual trading days | AA12: 10 | AB12: 1000 | AC12: 1500 | AD12: $1,500 for first 3 payouts; later rules/live consolidation apply | AE12: 1 | AF12: Weekly processing on Wednesday | AG12: $2,600 safety reserve | AH12: Reserve remains; after 3 payouts accounts may consolidate to one live account | AI12: 1099-MISC/W-8BEN stated on help page | AL12: High | AM12: Outdated help text, vague strategy enforcement reports, post-pass/live consolidation complexity | AN12: 100% first $10k stated, $2.5k drawdown, broad instruments | AO12: Operating for several years; exact founding date needs verification | AP12: Public documentation appears dated and internally inconsistent | AQ12: High-priority verification: account cap, consistency %, copy trading, and post-third-payout consolidation. | AR12: https://bulenox.com/member/signup https://bulenox.com/help/qualification-account/ https://bulenox.com/help/master-account/
A13: Earn2Trade | B13: TCP50 | C13: 50000 | D13: 190 | F13: Monthly | G13: 139 | H13: 0 | I13: 1 | J13: No practical five-account stack; verify partner allocation | K13: No | L13: Rithmic/Tradovate; NinjaTrader, Finamark, TradingView options | M13: CME, CBOT, NYMEX, COMEX futures | N13: 3000 | O13: 2000 | P13: $1,100 | Q13: EOD drawdown, but open/closed equity monitored intraday | R13: 10 | S13: Consistency required; exact formula needs verification | T13: Approved trading times only | U13: No | V13: No | W13: Progression ladder | X13: Up to 6 | Y13: Copy traders prohibited; automation needs approval | Z13: Funded withdrawals over $100; first must also cover $139 setup | AA13: 1 | AB13: 100 | AC13: 3000 | AD13: No simple cycle cap; TCP scaling model | AE13: 0.8 | AF13: On request through partner/Rise | AG13: First profit must cover $100 minimum + $139 setup | AH13: Withdraw profit target to advance to larger account in TCP | AI13: Rise/contractor onboarding; verify forms | AJ13: 4.7 | AK13: 4828 | AL13: Low | AM13: More restrictive rules, 10-day test, no copier, partner/data/setup complexity | AN13: Founded 2016, transparent pass/withdrawal statistics, education, genuine live-account option | AO13: Founded 2016 | AP13: Very transparent disclosures, but not designed for account stacking | AQ13: Not a fit for five copied accounts. Confirm partner funding/account-allocation policy. | AR13: https://www.earn2trade.com/purchase https://help.earn2trade.com/en/articles/5941958-what-are-the-trader-career-path-rules https://help.earn2trade.com/en/articles/6877574-what-offer-will-i-receive-upon-completing-the-trader-career-path https://www.trustpilot.com/review/www.earn2trade.com
A14: Elite Trader Funding | B14: 50K EOD Evaluation | C14: 50000 | D14: 295 | F14: Monthly | G14: 0 | H14: 80 | I14: 5 | J14: Needs verification | K14: Needs verification | L14: NinjaTrader/Rithmic ecosystem; free license/data stated | M14: CME-group futures; verify list | N14: 3000 | O14: 2000 | P14: $1,100 | Q14: EOD trailing | R14: 5 | S14: Needs verification | T14: Needs verification | U14: Needs verification | V14: No | W14: 8 minis / 80 micros | X14: 8 minis / 80 micros; no scaling in evaluation | Y14: Needs verification | Z14: Active Trade Day cycles; exact 50K EOD table needs verification | AA14: 10 | AB14: 500 | AC14: 1500 | AD14: $25,000 aggregate trader cap before live transition stated | AE14: 0.9 | AF14: By payout cycle | AG14: Needs verification | AH14: Needs verification | AI14: Needs verification | AL14: High | AM14: Complex product catalog and payout-cycle rules; current public tables difficult to extract | AN14: High contract limit, EOD option, established platform/data package | AO14: Operating several years | AP14: Current public information is fragmented | AQ14: Verify current checkout price, account cap, payout cycle/caps, split, copier and funded monthly fee. | AR14: https://shop.elitetraderfunding.com/products/50k-end-of-day-drawdown-evaluation-gift-card https://help.elitetraderfunding.com/help/etf-payout-amounts-by-account-type

Sheet Five Account Cost Model
A1: Five Account Cost Model
A2: Assumes all five evaluations pass in one billing period with no resets. Trading-profit buffers are not cash fees.
A4: Company | B4: Plan | C4: Normal Eval x5 | D4: Promo / Bundle Eval x5 | E4: Monthly Recurring x5 | F4: Activation x5 | G4: Funded Monthly x5 | H4: Cost to Funded (1 month) | I4: Est. Cash Cost to First Payout | J4: Trading Profit Needed to Unlock / Acct | K4: Max First Payout x5 (Gross) | L4: Max First Payout x5 (Net) | M4: Realistic First Payout x5 (Net) | N4: Break-Even Cash Amount | O4: Five Funded Feasible? | P4: Notes
A5: Apex Trader Funding | B5: 50K EOD Evaluation | C5: ='Full Comparison'!D5*5 | D5: ='Full Comparison'!E5*5 | E5: =IF('Full Comparison'!F5="Monthly",'Full Comparison'!D5*5,0) | F5: ='Full Comparison'!G5*5 | G5: ='Full Comparison'!H5*5 | H5: =C5+F5 | I5: =H5+G5 | J5: 2600 | K5: ='Full Comparison'!AC5*5 | L5: =K5*'Full Comparison'!AE5 | M5: 5000 | N5: =I5 | O5: Yes | P5: Normal $450 and $119 activation are volatile; confirm checkout before purchase.
A6: Alpha Futures | B6: 50K Standard Evaluation | C6: ='Full Comparison'!D6*5 | E6: =IF('Full Comparison'!F6="Monthly",'Full Comparison'!D6*5,0) | F6: ='Full Comparison'!G6*5 | G6: ='Full Comparison'!H6*5 | H6: =C6+F6 | I6: =H6+G6 | J6: 2000 | K6: ='Full Comparison'!AC6*5 | L6: =K6*'Full Comparison'!AE6 | M6: 4500 | N6: =I6 | O6: No (3 qualified max) | P6: Current site displays multiple plan variants. Confirm Standard price, activation fee, and five-account objective.
A7: Tradeify | B7: 50K Select Evaluation | C7: ='Full Comparison'!D7*5 | D7: ='Full Comparison'!E7*5 | E7: =IF('Full Comparison'!F7="Monthly",'Full Comparison'!D7*5,0) | F7: ='Full Comparison'!G7*5 | G7: ='Full Comparison'!H7*5 | H7: =C7+F7 | I7: =H7+G7 | J7: 2100 | K7: ='Full Comparison'!AC7*5 | L7: =K7*'Full Comparison'!AE7 | M7: 5625 | N7: =I7 | O7: Yes | P7: Overnight and automation specifics should be confirmed for selected broker/path.
A8: Lucid Trading | B8: 50K LucidPro Evaluation | C8: ='Full Comparison'!D8*5 | D8: ='Full Comparison'!E8*5 | E8: =IF('Full Comparison'!F8="Monthly",'Full Comparison'!D8*5,0) | F8: ='Full Comparison'!G8*5 | G8: ='Full Comparison'!H8*5 | H8: =C8+F8 | I8: =H8+G8 | J8: 2600 | K8: ='Full Comparison'!AC8*5 | L8: =K8*'Full Comparison'!AE8 | M8: 5625 | N8: =I8 | O8: Yes | P8: Obtain written confirmation for bots/copiers, news and overnight policy.
A9: Topstep | B9: 50K Standard Trading Combine | C9: ='Full Comparison'!D9*5 | E9: =IF('Full Comparison'!F9="Monthly",'Full Comparison'!D9*5,0) | F9: ='Full Comparison'!G9*5 | G9: ='Full Comparison'!H9*5 | H9: =C9+F9 | I9: =H9+G9 | J9: 2500 | K9: ='Full Comparison'!AC9*5 | L9: =K9*'Full Comparison'!AE9 | M9: 5625 | N9: =I9 | O9: Yes (5 active XFA max; verify purchase limits) | P9: Confirm current XFA count and selected payout path immediately before purchase.
A10: Take Profit Trader | B10: 50K Test | C10: ='Full Comparison'!D10*5 | D10: ='Full Comparison'!E10*5 | E10: =IF('Full Comparison'!F10="Monthly",'Full Comparison'!D10*5,0) | F10: ='Full Comparison'!G10*5 | G10: ='Full Comparison'!H10*5 | H10: =C10+F10 | I10: =H10+G10 | J10: 2000 | K10: ='Full Comparison'!AC10*5 | L10: =K10*'Full Comparison'!AE10 | M10: 6000 | N10: =I10 | O10: Yes | P10: Confirm current $2,000 drawdown, $130 activation, and PRO+ transition policy.
A11: MyFundedFutures | B11: 50K Flex | C11: ='Full Comparison'!D11*5 | D11: ='Full Comparison'!E11*5 | E11: =IF('Full Comparison'!F11="Monthly",'Full Comparison'!D11*5,0) | F11: ='Full Comparison'!G11*5 | G11: ='Full Comparison'!H11*5 | H11: =C11+F11 | I11: =H11+G11 | J11: 1000 | K11: ='Full Comparison'!AC11*5 | L11: =K11*'Full Comparison'!AE11 | M11: 4000 | N11: =I11 | O11: No (new 50K Flex sim-funded cap is 3) | P11: Not suitable for five funded 50K Flex accounts under the current 3-account cap.
A12: Bulenox | B12: 50K Option 2 EOD/Scaling | C12: ='Full Comparison'!D12*5 | E12: =IF('Full Comparison'!F12="Monthly",'Full Comparison'!D12*5,0) | F12: ='Full Comparison'!G12*5 | G12: ='Full Comparison'!H12*5 | H12: =C12+F12 | I12: =H12+G12 | J12: 3600 | K12: ='Full Comparison'!AC12*5 | L12: =K12*'Full Comparison'!AE12 | M12: 5000 | N12: =I12 | O12: Needs verification; post-pass gating reported | P12: High-priority verification: account cap, consistency %, copy trading, and post-third-payout consolidation.
A13: Earn2Trade | B13: TCP50 | C13: ='Full Comparison'!D13*5 | E13: =IF('Full Comparison'!F13="Monthly",'Full Comparison'!D13*5,0) | F13: ='Full Comparison'!G13*5 | G13: ='Full Comparison'!H13*5 | H13: =C13+F13 | I13: =H13+G13 | J13: 239 | K13: ='Full Comparison'!AC13*5 | L13: =K13*'Full Comparison'!AE13 | M13: 4000 | N13: =I13 | O13: No practical five-account stack; verify partner allocation | P13: Not a fit for five copied accounts. Confirm partner funding/account-allocation policy.
A14: Elite Trader Funding | B14: 50K EOD Evaluation | C14: ='Full Comparison'!D14*5 | E14: =IF('Full Comparison'!F14="Monthly",'Full Comparison'!D14*5,0) | F14: ='Full Comparison'!G14*5 | G14: ='Full Comparison'!H14*5 | H14: =C14+F14 | I14: =H14+G14 | J14: 2500 | K14: ='Full Comparison'!AC14*5 | L14: =K14*'Full Comparison'!AE14 | M14: 3375 | N14: =I14 | O14: Needs verification | P14: Verify current checkout price, account cap, payout cycle/caps, split, copier and funded monthly fee.

Sheet Rules Matrix
A1: Rules Matrix
A2: Side-by-side evaluation and funded-rule comparison.
A4: Company | B4: Plan | C4: Drawdown Type | D4: Profit Target | E4: Max Drawdown | F4: Daily Loss Limit | G4: Min Days | H4: Consistency | I4: News | J4: Overnight | K4: Contract Limits | L4: Copy Trading | M4: Automation
A5: Apex Trader Funding | B5: 50K EOD Evaluation | C5: EOD trailing; enforced next session | D5: 3000 | E5: 2000 | F5: $1,000 fixed session DLL | G5: 1 | H5: None to pass; 50% at payout | I5: Allowed, subject to conduct rules | J5: Intraday only; flat by close | K5: 6 (official support page table should be rechecked at checkout) -> 6 | L5: Yes, own accounts; avoid prohibited coordination/hedging | M5: Restricted; verify current prohibited-conduct policy
A6: Alpha Futures | B6: 50K Standard Evaluation | C6: EOD trailing, locks near starting balance | D6: 3000 | E6: 2000 | F6: None eval; 2% daily loss guard qualified | G6: 2 | H6: 50% eval; 40% Standard qualified | I6: Eval yes; funded varies by plan | J6: No; flat by 4:20 PM ET | K6: Scaling plan -> 5 minis / 50 micros | L6: Own-account copying may be supported; copying another trader prohibited | M6: Algorithmic support reported; verify copier/bot policy
A7: Tradeify | B7: 50K Select Evaluation | C7: EOD trailing; locks at $50,100 | D7: 3000 | E7: 2000 | F7: None in Select eval/Flex funded | G7: 3 | H7: 40% eval; none on Select Flex funded | I7: Allowed with restrictions around prohibited conduct | J7: Needs verification | K7: 2 minis / 20 micros funded -> 4 minis / 40 micros | L7: Yes across own accounts; no hedging/circumvention | M7: Copiers supported; automation policy needs verification
A8: Lucid Trading | B8: 50K LucidPro Evaluation | C8: EOD trailing | D8: 3000 | E8: 2000 | F8: $1,200 | G8: 1 | H8: None eval; 40% funded payout cycle | I8: Needs verification by plan | J8: Needs verification | K8: 4 minis / 40 micros -> 4 minis / 40 micros | L8: Own-account copying appears supported; confirm current automation policy | M8: Needs verification in writing
A9: Topstep | B9: 50K Standard Trading Combine | C9: Trailing Maximum Loss Limit based on balance | D9: 3000 | E9: 2000 | F9: Optional soft DLL discount; no required DLL in Combine | G9: 2 | H9: 50% Combine; choose Standard or 40% Consistency XFA | I9: Generally allowed; follow permitted trading hours | J9: No; intraday futures hours | K9: Scaling plan in funded -> 5 minis / 50 micros in Combine | L9: TopstepX trade copier available; strict no cross-account hedging | M9: Trade copier supported; automation subject to prohibited-conduct rules
A10: Take Profit Trader | B10: 50K Test | C10: EOD trailing in Test; PRO mechanics tighten around buffer | D10: 3000 | E10: 2000 | F10: None on current Test; confirm at checkout | G10: 5 | H10: 50% Test; none PRO | I10: Allowed | J10: No | K10: Scaling plan -> 6 minis / 60 micros | L10: Yes across own accounts; no hedging | M10: Copiers allowed; bots/EAs restricted
A11: MyFundedFutures | B11: 50K Flex | C11: EOD trailing in eval and Flex sim-funded | D11: 3000 | E11: 2000 | F11: None (optional lower-priced DLL add-on variant) | G11: 2 | H11: 50% eval only; none payout stage | I11: Allowed | J11: Needs verification | K11: 2 minis / 20 micros -> 5 minis / 50 micros after scaling | L11: Own-account copier supported subject to anti-hedging rules | M11: Copiers supported; bot policy needs verification
A12: Bulenox | B12: 50K Option 2 EOD/Scaling | C12: EOD trailing/scaling | D12: 3000 | E12: 2500 | F12: $1,100 soft daily suspension on Option 2 | G12: 5 | H12: Consistency applies in Master payout stage; exact current % needs verification | I12: Needs verification | J12: Limited micros only on legacy help text | K12: 2 minis -> 7 after scaling | L12: Needs verification | M12: Needs verification
A13: Earn2Trade | B13: TCP50 | C13: EOD drawdown, but open/closed equity monitored intraday | D13: 3000 | E13: 2000 | F13: $1,100 | G13: 10 | H13: Consistency required; exact formula needs verification | I13: Approved trading times only | J13: No | K13: Progression ladder -> Up to 6 | L13: No | M13: Copy traders prohibited; automation needs approval
A14: Elite Trader Funding | B14: 50K EOD Evaluation | C14: EOD trailing | D14: 3000 | E14: 2000 | F14: $1,100 | G14: 5 | H14: Needs verification | I14: Needs verification | J14: Needs verification | K14: 8 minis / 80 micros -> 8 minis / 80 micros; no scaling in evaluation | L14: Needs verification | M14: Needs verification

Sheet Payout Matrix
A1: Payout Matrix
A2: Net payout values depend on each firm's stated profit split.
A4: Company | B4: First Payout Timing | C4: Required Days | D4: Minimum Payout | E4: Max First Payout | F4: Recurring Cap | G4: Profit Split | H4: Frequency | I4: Buffer Rules | J4: Payout Effect / Caps
A5: Apex Trader Funding | B5: After 5 qualifying days at $250+ each | C5: 5 | D5: 500 | E5: 1500 | F5: Payouts 1-6: $1.5k, $1.5k, $2k, $2.5k, $2.5k, $3k | G5: 1 | H5: Up to weekly | I5: $2,100 safety net; $52,600 balance to request $500 | J5: Only profit above safety net withdrawable; PA closes after payout 6
A6: Alpha Futures | B6: After 5 winning days of $200+ | C6: 5 | D6: 200 | E6: 1500 | F6: $1,500/request on current 50K plan shown | G6: 0.9 | H6: Up to 4x/month | I6: May withdraw up to 50% of profit/request | J6: Drawdown protection remains important
A7: Tradeify | B7: Select Flex after 5 winning days; Daily path can qualify daily | C7: 5 | D7: 250 | E7: 2000 | F7: Flex: generally 50% of profit; Daily capped $1,000 on 50K | G7: 0.9 | H7: Daily eligibility depending on selected path | I7: Path-specific; Select Flex lock trigger $52,100 | J7: MLL locks at $50,100 after threshold/payout mechanics
A8: Lucid Trading | B8: Any day after $500 cycle profit, 40% consistency, and buffer | C8: 3 | D8: 500 | E8: 2000 | F8: $2,500 from payout 2 onward | G8: 0.9 | H8: On demand; no fixed window | I8: $52,100; payout only above buffer | J8: Payout reduces cushion above locked loss floor
A9: Topstep | B9: Standard: 5 days $150+; Consistency: 3 days plus 40% | C9: 5 | D9: 125 | E9: 2000 | F9: $2,000 Standard / $3,000 Consistency per request on new 50K | G9: 0.9 | H9: Weekly; daily after 30 winning live days | I9: Can request 50% of account balance/profit subject to cap | J9: Payout can reduce buying power and account cushion
A10: Take Profit Trader | B10: Day one after reaching $52,000 buffer | C10: 1 | D10: 0 | E10: 5000 | F10: No stated cycle cap above buffer; firm may move trader to PRO+ live | G10: 0.8 | H10: Daily/on demand | I10: $2,000 buffer; normal withdrawals only once balance reaches $52,000 | J10: Withdrawing above buffer preserves floor; inside-buffer withdrawal generally terminates account
A11: MyFundedFutures | B11: 5 days at $150+ net | C11: 5 | D11: 500 | E11: 2000 | F11: 50% of net profit up to $2,000/cycle; max 5 sim payouts | G11: 0.8 | H11: Weekly/performance based | I11: No buffer requirement | J11: After first payout max loss becomes fixed at $100
A12: Bulenox | B12: After 10 individual trading days | C12: 10 | D12: 1000 | E12: 1500 | F12: $1,500 for first 3 payouts; later rules/live consolidation apply | G12: 1 | H12: Weekly processing on Wednesday | I12: $2,600 safety reserve | J12: Reserve remains; after 3 payouts accounts may consolidate to one live account
A13: Earn2Trade | B13: Funded withdrawals over $100; first must also cover $139 setup | C13: 1 | D13: 100 | E13: 3000 | F13: No simple cycle cap; TCP scaling model | G13: 0.8 | H13: On request through partner/Rise | I13: First profit must cover $100 minimum + $139 setup | J13: Withdraw profit target to advance to larger account in TCP
A14: Elite Trader Funding | B14: Active Trade Day cycles; exact 50K EOD table needs verification | C14: 10 | D14: 500 | E14: 1500 | F14: $25,000 aggregate trader cap before live transition stated | G14: 0.9 | H14: By payout cycle | I14: Needs verification | J14: Needs verification

Sheet Reputation - Risk
A1: Reputation / Risk
A2: Review ratings are snapshots, not proof of payout reliability. Themes combine public reviews and documentation quality.
A4: Company | B4: Trustpilot | C4: Reviews | D4: Common Complaints | E4: Common Praise | F4: Rule-Change Risk | G4: Payout-Denial Risk | H4: Overall Risk | I4: Longevity | J4: Transparency | K4: Review Source
A5: Apex Trader Funding | B5: 4.3 | C5: 19517 | D5: Historical payout-review/rule-change complaints; promo/base pricing changes; strict conduct rules | E5: Large community, broad platform support, 100% current payout split, up to 20 accounts | F5: High | G5: Medium | H5: Medium | I5: Operating since 2021 | J5: 2026 program redesign; price is volatile and promo-led | K5: https://www.trustpilot.com/review/apextraderfunding.com
A6: Alpha Futures | B6: 4.9 | C6: 3952 | D6: New proprietary platform issues; plan naming/pricing changes; consistency complexity | E6: Very high recent support ratings, EOD drawdown, fast support | F6: Medium | G6: Medium | H6: Medium | I6: Newer firm; shorter operating history than Topstep/Earn2Trade | J6: Current site and help-center plan labels conflict in places | K6: https://www.trustpilot.com/review/alpha-futures.com
A7: Tradeify | B7: 4.6 | C7: 2961 | D7: Some KYC/account closure and support-resolution complaints; rules have evolved quickly | E7: Fast payouts/support, one-time pricing, permanent five-pack discount, flexible payout path | F7: Medium | G7: Low | H7: Low | I7: Launched 2024 | J7: Excellent current pricing/rules documentation | K7: https://www.trustpilot.com/review/tradeify.co
A8: Lucid Trading | B8: 4.7 | C8: 4125 | D8: Some closures/automation disputes and support delays; company is relatively new | E8: Very fast payout reports, clean dashboard, clear payout article, no activation fee | F8: Medium | G8: Medium | H8: Medium | I8: Operating since 2025 | J8: Good help center; checkout pricing/promos change | K8: https://www.trustpilot.com/review/lucidtrading.com
A9: Topstep | B9: 3.5 | C9: 14166 | D9: Strict hedging enforcement, subscription billing complaints, platform incidents | E9: 12+ year history, real live progression, strong education, clear official help center | F9: Medium | G9: Low | H9: Low | I9: Founded 2012 | J9: Best-in-class official documentation, though rules update often | K9: https://www.trustpilot.com/review/topstep.com
A10: Take Profit Trader | B10: 4.4 | C10: 9562 | D10: PRO+ transition/support delays; conflicting third-party drawdown figures; monthly cost | E10: Daily withdrawals, long payout history, responsive support, clear core buffer concept | F10: Medium | G10: Medium | H10: Medium | I10: Operating since 2022 | J10: Official help center clear on payouts; public pricing page less searchable | K10: https://www.trustpilot.com/review/takeprofittrader.com
A11: MyFundedFutures | B11: 4.9 | C11: 18858 | D11: Frequent plan changes; strict post-payout $100 loss floor; KYC/support complaints | E11: No payout buffer, strong support ratings, clear current plan page, path to live after 5 payouts | F11: High | G11: Medium | H11: Medium | I11: Operating since 2023 | J11: Current pages are detailed but product lineup changes frequently | K11: https://www.trustpilot.com/review/myfundedfutures.com
A12: Bulenox | D12: Outdated help text, vague strategy enforcement reports, post-pass/live consolidation complexity | E12: 100% first $10k stated, $2.5k drawdown, broad instruments | F12: High | G12: High | H12: High | I12: Operating for several years; exact founding date needs verification | J12: Public documentation appears dated and internally inconsistent | K12: Needs verification
A13: Earn2Trade | B13: 4.7 | C13: 4828 | D13: More restrictive rules, 10-day test, no copier, partner/data/setup complexity | E13: Founded 2016, transparent pass/withdrawal statistics, education, genuine live-account option | F13: Medium | G13: Low | H13: Low | I13: Founded 2016 | J13: Very transparent disclosures, but not designed for account stacking | K13: https://www.trustpilot.com/review/www.earn2trade.com
A14: Elite Trader Funding | D14: Complex product catalog and payout-cycle rules; current public tables difficult to extract | E14: High contract limit, EOD option, established platform/data package | F14: High | G14: High | H14: High | I14: Operating several years | J14: Current public information is fragmented | K14: Needs verification

Sheet Scores & Dashboard
A1: Weighted Scorecard & Dashboard
A2: Weights: Cost 20%, Rules/Drawdown 20%, Payout 25%, Multi-account 15%, Reputation/Transparency 20%. Inputs scored 1-10.
A3: Visible scoring weights -> | G3: 0.2 | H3: 0.2 | I3: 0.25 | J3: 0.15 | K3: 0.2
A5: Company | B5: Cost (1-10) | C5: Rules (1-10) | D5: Payout (1-10) | E5: Multi-Account (1-10) | F5: Reputation (1-10) | G5: Cost Weight | H5: Rules Weight | I5: Payout Weight | J5: Multi Weight | K5: Reputation Weight | L5: Weighted Score / 100 | M5: Cost to First Payout x5 | N5: Max First Payout x5 Net | O5: Payout Flexibility
A6: Apex Trader Funding | B6: 8 | C6: 7 | D6: 7 | E6: 10 | F6: 7 | G6: 0.2 | H6: 0.2 | I6: 0.25 | J6: 0.15 | K6: 0.2 | L6: =SUMPRODUCT(B6:F6,G6:K6)*10 | M6: ='Five Account Cost Model'!I5 | N6: ='Five Account Cost Model'!L5 | O6: 70
A7: Alpha Futures | B7: 9 | C7: 7 | D7: 7 | E7: 4 | F7: 8 | G7: 0.2 | H7: 0.2 | I7: 0.25 | J7: 0.15 | K7: 0.2 | L7: =SUMPRODUCT(B7:F7,G7:K7)*10 | M7: ='Five Account Cost Model'!I6 | N7: ='Five Account Cost Model'!L6 | O7: 70
A8: Tradeify | B8: 9 | C8: 9 | D8: 9 | E8: 10 | F8: 9 | G8: 0.2 | H8: 0.2 | I8: 0.25 | J8: 0.15 | K8: 0.2 | L8: =SUMPRODUCT(B8:F8,G8:K8)*10 | M8: ='Five Account Cost Model'!I7 | N8: ='Five Account Cost Model'!L7 | O8: 90
A9: Lucid Trading | B9: 8 | C9: 8 | D9: 9 | E9: 9 | F9: 8 | G9: 0.2 | H9: 0.2 | I9: 0.25 | J9: 0.15 | K9: 0.2 | L9: =SUMPRODUCT(B9:F9,G9:K9)*10 | M9: ='Five Account Cost Model'!I8 | N9: ='Five Account Cost Model'!L8 | O9: 90
A10: Topstep | B10: 8 | C10: 8 | D10: 8 | E10: 9 | F10: 9 | G10: 0.2 | H10: 0.2 | I10: 0.25 | J10: 0.15 | K10: 0.2 | L10: =SUMPRODUCT(B10:F10,G10:K10)*10 | M10: ='Five Account Cost Model'!I9 | N10: ='Five Account Cost Model'!L9 | O10: 80
A11: Take Profit Trader | B11: 6 | C11: 8 | D11: 10 | E11: 9 | F11: 8 | G11: 0.2 | H11: 0.2 | I11: 0.25 | J11: 0.15 | K11: 0.2 | L11: =SUMPRODUCT(B11:F11,G11:K11)*10 | M11: ='Five Account Cost Model'!I10 | N11: ='Five Account Cost Model'!L10 | O11: 100
A12: MyFundedFutures | B12: 8 | C12: 9 | D12: 8 | E12: 3 | F12: 8 | G12: 0.2 | H12: 0.2 | I12: 0.25 | J12: 0.15 | K12: 0.2 | L12: =SUMPRODUCT(B12:F12,G12:K12)*10 | M12: ='Five Account Cost Model'!I11 | N12: ='Five Account Cost Model'!L11 | O12: 80
A13: Bulenox | B13: 5 | C13: 6 | D13: 5 | E13: 4 | F13: 4 | G13: 0.2 | H13: 0.2 | I13: 0.25 | J13: 0.15 | K13: 0.2 | L13: =SUMPRODUCT(B13:F13,G13:K13)*10 | M13: ='Five Account Cost Model'!I12 | N13: ='Five Account Cost Model'!L12 | O13: 50
A14: Earn2Trade | B14: 5 | C14: 5 | D14: 6 | E14: 1 | F14: 9 | G14: 0.2 | H14: 0.2 | I14: 0.25 | J14: 0.15 | K14: 0.2 | L14: =SUMPRODUCT(B14:F14,G14:K14)*10 | M14: ='Five Account Cost Model'!I13 | N14: ='Five Account Cost Model'!L13 | O14: 60
A15: Elite Trader Funding | B15: 3 | C15: 6 | D15: 5 | E15: 6 | F15: 4 | G15: 0.2 | H15: 0.2 | I15: 0.25 | J15: 0.15 | K15: 0.2 | L15: =SUMPRODUCT(B15:F15,G15:K15)*10 | M15: ='Five Account Cost Model'!I14 | N15: ='Five Account Cost Model'!L14 | O15: 50

Sheet Source Links
A1: Source Links
A2: Official company pages are prioritized. Third-party pricing references are labeled and should be verified at checkout.
A4: ID | B4: Source | C4: Type | D4: URL | E4: Accessed | F4: Notes
A5: 1 | B5: Apex rules | C5: Official | D5: https://support.apextraderfunding.com/hc/en-us/articles/46724640813083-EOD-Evaluations | E5: 46179
A6: 2 | B6: Apex payouts | C6: Official | D6: https://support.apextraderfunding.com/hc/en-us/articles/47205823183003-EOD-Payouts | E6: 46179
A7: 3 | B7: Apex pricing reference | C7: Third-party pricing reference | D7: https://propfirmmatch.com/futures/prop-firm-challenges/apex-trader-funding-standard-eod-1-step-50k | E7: 46179 | F7: Volatile; confirm at checkout
A8: 4 | B8: Alpha overview | C8: Official | D8: https://help.alpha-futures.com/en/articles/9491980-alpha-futures-evaluation-qualified-trader-overview | E8: 46179
A9: 5 | B9: Alpha pricing | C9: Official | D9: https://alpha-futures.com/how-it-works | E9: 46179
A10: 6 | B10: Alpha terms | C10: Official | D10: https://alpha-futures.com/terms-and-conditions | E10: 46179
A11: 7 | B11: Tradeify pricing | C11: Official | D11: https://help.tradeify.co/en/articles/14369021-tradeify-pricing-reference | E11: 46179
A12: 8 | B12: Tradeify eval | C12: Official | D12: https://help.tradeify.co/en/articles/12853921-select-evaluation-accounts | E12: 46179
A13: 9 | B13: Tradeify payouts | C13: Official | D13: https://help.tradeify.co/en/articles/12853966-select-flex-and-select-daily-payout-policies | E13: 46179
A14: 10 | B14: Lucid pricing | C14: Official | D14: https://www.lucidtrading.com/ | E14: 46179
A15: 11 | B15: Lucid product | C15: Official | D15: https://lucidtrading.com/product/lucidtest-50k/ | E15: 46179
A16: 12 | B16: Lucid payouts | C16: Official | D16: https://support.lucidtrading.com/en/articles/12890092-lucidpro-payouts | E16: 46179
A17: 13 | B17: Topstep pricing | C17: Official | D17: https://help.topstep.com/en/articles/9208217-topstep-pricing | E17: 46179
A18: 14 | B18: Topstep parameters | C18: Official | D18: https://help.topstep.com/en/articles/8284197-trading-combine-parameters | E18: 46179
A19: 15 | B19: Topstep payouts | C19: Official | D19: https://help.topstep.com/en/articles/8284233-topstep-payout-policy/ | E19: 46179
A20: 16 | B20: TPT pricing reference | C20: Third-party pricing reference | D20: https://funded.now/propfirm/takeprofit-trader/50000 | E20: 46179 | F20: Volatile; confirm at checkout
A21: 17 | B21: TPT payouts | C21: Official | D21: https://takeprofittraderhelp.zendesk.com/hc/en-us/articles/15172219527581-PRO-Account-Profit-Split-Withdrawal-Rules | E21: 46179
A22: 18 | B22: MFFU rules | C22: Official | D22: https://myfundedfutures.com/plans/flex | E22: 46179
A23: 19 | B23: MFFU pricing/accounts | C23: Official | D23: https://help.myfundedfutures.com/en/articles/11802636-traders-evaluation-simplified | E23: 46179
A24: 20 | B24: Bulenox pricing | C24: Official | D24: https://bulenox.com/member/signup | E24: 46179
A25: 21 | B25: Bulenox rules | C25: Official | D25: https://bulenox.com/help/qualification-account/ | E25: 46179
A26: 22 | B26: Bulenox payouts | C26: Official | D26: https://bulenox.com/help/master-account/ | E26: 46179
A27: 23 | B27: Earn2Trade pricing | C27: Official | D27: https://www.earn2trade.com/purchase | E27: 46179
A28: 24 | B28: Earn2Trade rules | C28: Official | D28: https://help.earn2trade.com/en/articles/5941958-what-are-the-trader-career-path-rules | E28: 46179
A29: 25 | B29: Earn2Trade funded | C29: Official | D29: https://help.earn2trade.com/en/articles/6877574-what-offer-will-i-receive-upon-completing-the-trader-career-path | E29: 46179
A30: 26 | B30: Elite pricing | C30: Official | D30: https://shop.elitetraderfunding.com/products/50k-end-of-day-drawdown-evaluation-gift-card | E30: 46179
A31: 27 | B31: Elite payouts | C31: Official | D31: https://help.elitetraderfunding.com/help/etf-payout-amounts-by-account-type | E31: 46179
A32: 28 | B32: Trustpilot Apex | C32: Review platform | D32: https://www.trustpilot.com/review/apextraderfunding.com | E32: 46179
... A39: 35 | B39: Trustpilot Earn2Trade | C39: Review platform | D39: https://www.trustpilot.com/review/www.earn2trade.com | E39: 46179
